[{"time": "2022-04-07 08:10:00", "val": 459.0, "median": null, "p90": null, "p10": null}, {"time": "2022-04-07 08:20:00", "val": 499.0, "median": null, "p90": null, "p10": null}, {"time": "2022-04-07 08:30:00", "val": 534.0, "median": null, "p90": null, "p10": null}, {"time": "2022-04-07 08:40:00", "val": 568.0, "median": null, "p90": null, "p10": null}, {"time": "2022-04-07 08:50:00", "val": 601.0, "median": null, "p90": null, "p10": null}, {"time": "2022-04-07 09:00:00", "val": 634.0, "median": null, "p90": null, "p10": null}, {"time": "2022-04-07 09:10:00", "val": 671.0, "median": null, "p90": null, "p10": null}, {"time": "2022-04-07 09:20:00", "val": 700.0, "median": null, "p90": null, "p10": null}, {"time": "2022-04-07 09:30:00", "val": 727.0, "median": null, "p90": null, "p10": null}, {"time": "2022-04-07 09:40:00", "val": 753.0, "median": null, "p90": null, "p10": null}, {"time": "2022-04-07 09:50:00", "val": 779.0, "median": null, "p90": null, "p10": null}, {"time": "2022-04-07 10:00:00", "val": 801.0, "median": null, "p90": null, "p10": null}, {"time": "2022-04-07 10:10:00", "val": 825.0, "median": null, "p90": null, "p10": null}, {"time": "2022-04-07 10:20:00", "val": 848.0, "median": null, "p90": null, "p10": null}, {"time": "2022-04-07 10:30:00", "val": 863.0, "median": null, "p90": null, "p10": null}, {"time": "2022-04-07 10:40:00", "val": 879.0, "median": null, "p90": null, "p10": null}, {"time": "2022-04-07 10:50:00", "val": 903.0, "median": null, "p90": null, "p10": null}, {"time": "2022-04-07 11:00:00", "val": 924.0, "median": null, "p90": null, "p10": null}, {"time": "2022-04-07 11:10:00", "val": 928.0, "median": null, "p90": null, "p10": null}, {"time": "2022-04-07 11:20:00", "val": 935.0, "median": null, "p90": null, "p10": null}, {"time": "2022-04-07 11:30:00", "val": 939.0, "median": null, "p90": null, "p10": null}, {"time": "2022-04-07 11:40:00", "val": 935.0, "median": null, "p90": null, "p10": null}, {"time": "2022-04-07 11:50:00", "val": 937.0, "median": null, "p90": null, "p10": null}, {"time": "2022-04-07 12:00:00", "val": 925.0, "median": null, "p90": null, "p10": null}, {"time": "2022-04-07 12:10:00", "val": 916.0, "median": null, "p90": null, "p10": null}, {"time": "2022-04-07 12:20:00", "val": 890.0, "median": null, "p90": null, "p10": null}, {"time": "2022-04-07 12:30:00", "val": 868.0, "median": null, "p90": null, "p10": null}, {"time": "2022-04-07 12:40:00", "val": 873.0, "median": null, "p90": null, "p10": null}, {"time": "2022-04-07 12:50:00", "val": 882.0, "median": null, "p90": null, "p10": null}, {"time": "2022-04-07 13:00:00", "val": 843.0, "median": null, "p90": null, "p10": null}, {"time": "2022-04-07 13:10:00", "val": 810.0, "median": null, "p90": null, "p10": null}, {"time": "2022-04-07 13:20:00", "val": 695.0, "median": null, "p90": null, "p10": null}, {"time": "2022-04-07 13:30:00", "val": 841.0, "median": null, "p90": null, "p10": null}, {"time": "2022-04-07 13:40:00", "val": 748.0, "median": null, "p90": null, "p10": null}, {"time": "2022-04-07 13:50:00", "val": 784.0, "median": null, "p90": null, "p10": null}, {"time": "2022-04-07 14:00:00", "val": 737.0, "median": null, "p90": null, "p10": null}, {"time": "2022-04-07 14:10:00", "val": 707.0, "median": null, "p90": null, "p10": null}, {"time": "2022-04-07 14:20:00", "val": 677.0, "median": null, "p90": null, "p10": null}, {"time": "2022-04-07 14:30:00", "val": 643.0, "median": null, "p90": null, "p10": null}, {"time": "2022-04-07 14:40:00", "val": 611.0, "median": null, "p90": null, "p10": null}, {"time": "2022-04-07 14:50:00", "val": 551.0, "median": null, "p90": null, "p10": null}, {"time": "2022-04-07 15:00:00", "val": 547.0, "median": null, "p90": null, "p10": null}, {"time": "2022-04-07 15:10:00", "val": 523.0, "median": null, "p90": null, "p10": null}, {"time": "2022-04-07 15:20:00", "val": 347.0, "median": null, "p90": null, "p10": null}, {"time": "2022-04-07 15:30:00", "val": 501.0, "median": null, "p90": null, "p10": null}, {"time": "2022-04-07 15:40:00", "val": 480.0, "median": null, "p90": null, "p10": null}, {"time": "2022-04-07 15:50:00", "val": 389.0, "median": null, "p90": null, "p10": null}, {"time": "2022-04-07 16:00:00", "val": 184.0, "median": null, "p90": null, "p10": null}, {"time": "2022-04-07 16:10:00", "val": 367.0, "median": null, "p90": null, "p10": null}, {"time": "2022-04-07 16:20:00", "val": 303.0, "median": null, "p90": null, "p10": null}, {"time": "2022-04-07 16:30:00", "val": 206.0, "median": null, "p90": null, "p10": null}, {"time": "2022-04-07 16:40:00", "val": 192.0, "median": null, "p90": null, "p10": null}, {"time": "2022-04-07 16:50:00", "val": 112.0, "median": null, "p90": null, "p10": null}, {"time": "2022-04-07 17:00:00", "val": 76.0, "median": null, "p90": null, "p10": null}, {"time": "2022-04-07 17:10:00", "val": 124.0, "median": null, "p90": null, "p10": null}, {"time": "2022-04-07 17:20:00", "val": 119.0, "median": null, "p90": null, "p10": null}, {"time": "2022-04-07 17:30:00", "val": 74.0, "median": null, "p90": null, "p10": null}, {"time": "2022-04-07 17:40:00", "val": 35.0, "median": null, "p90": null, "p10": null}, {"time": "2022-04-07 17:50:00", "val": 11.0, "median": null, "p90": null, "p10": null}, {"time": "2022-04-07 18:00:00", "val": 2.0, "median": null, "p90": null, "p10": null}, {"time": "2022-04-07 18:10:00", "val": 0.0, "median": null, "p90": null, "p10": null}, {"time": "2022-04-07 18:20:00", "val": 0.0, "median": null, "p90": null, "p10": null}, {"time": "2022-04-07 18:30:00", "val": 0.0, "median": null, "p90": null, "p10": null}, {"time": "2022-04-07 18:40:00", "val": 0.0, "median": null, "p90": null, "p10": null}, {"time": "2022-04-07 18:50:00", "val": 0.0, "median": null, "p90": null, "p10": null}, {"time": "2022-04-07 19:00:00", "val": 0.0, "median": null, "p90": null, "p10": null}, {"time": "2022-04-07 19:10:00", "val": 0.0, "median": null, "p90": null, "p10": null}, {"time": "2022-04-07 19:20:00", "val": 0.0, "median": null, "p90": null, "p10": null}, {"time": "2022-04-07 19:30:00", "val": 0.0, "median": null, "p90": null, "p10": null}, {"time": "2022-04-07 19:40:00", "val": 0.0, "median": null, "p90": null, "p10": null}, {"time": "2022-04-07 19:50:00", "val": 0.0, "median": null, "p90": null, "p10": null}, {"time": "2022-04-07 20:00:00", "val": 0.0, "median": null, "p90": null, "p10": null}, {"time": "2022-04-07 20:10:00", "val": 0.0, "median": null, "p90": null, "p10": null}, {"time": "2022-04-07 20:20:00", "val": 0.0, "median": null, "p90": null, "p10": null}, {"time": "2022-04-07 20:30:00", "val": 0.0, "median": null, "p90": null, "p10": null}, {"time": "2022-04-07 20:40:00", "val": 0.0, "median": null, "p90": null, "p10": null}, {"time": "2022-04-07 20:50:00", "val": 0.0, "median": null, "p90": null, "p10": null}, {"time": "2022-04-07 21:00:00", "val": 0.0, "median": null, "p90": null, "p10": null}, {"time": "2022-04-07 21:10:00", "val": 0.0, "median": null, "p90": null, "p10": null}, {"time": "2022-04-07 21:20:00", "val": 0.0, "median": null, "p90": null, "p10": null}, {"time": "2022-04-07 21:30:00", "val": 0.0, "median": null, "p90": null, "p10": null}, {"time": "2022-04-07 21:40:00", "val": 0.0, "median": null, "p90": null, "p10": null}, {"time": "2022-04-07 21:50:00", "val": 0.0, "median": null, "p90": null, "p10": null}, {"time": "2022-04-07 22:00:00", "val": 0.0, "median": null, "p90": null, "p10": null}, {"time": "2022-04-07 22:10:00", "val": 0.0, "median": null, "p90": null, "p10": null}, {"time": "2022-04-07 22:20:00", "val": 0.0, "median": null, "p90": null, "p10": null}, {"time": "2022-04-07 22:30:00", "val": 0.0, "median": null, "p90": null, "p10": null}, {"time": "2022-04-07 22:40:00", "val": 0.0, "median": null, "p90": null, "p10": null}, {"time": "2022-04-07 22:50:00", "val": 0.0, "median": null, "p90": null, "p10": null}, {"time": "2022-04-07 23:00:00", "val": 0.0, "median": null, "p90": null, "p10": null}, {"time": "2022-04-07 23:10:00", "val": 0.0, "median": null, "p90": null, "p10": null}, {"time": "2022-04-07 23:20:00", "val": 0.0, "median": null, "p90": null, "p10": null}, {"time": "2022-04-07 23:30:00", "val": 0.0, "median": null, "p90": null, "p10": null}, {"time": "2022-04-07 23:40:00", "val": 0.0, "median": null, "p90": null, "p10": null}, {"time": "2022-04-07 23:50:00", "val": 0.0, "median": null, "p90": null, "p10": null}, {"time": "2022-04-08 00:00:00", "val": 0.0, "median": null, "p90": null, "p10": null}, {"time": "2022-04-08 00:10:00", "val": 0.0, "median": null, "p90": null, "p10": null}, {"time": "2022-04-08 00:20:00", "val": 0.0, "median": null, "p90": null, "p10": null}, {"time": "2022-04-08 00:30:00", "val": 0.0, "median": null, "p90": null, "p10": null}, {"time": "2022-04-08 00:40:00", "val": 0.0, "median": null, "p90": null, "p10": null}, {"time": "2022-04-08 00:50:00", "val": 0.0, "median": null, "p90": null, "p10": null}, {"time": "2022-04-08 01:00:00", "val": 0.0, "median": null, "p90": null, "p10": null}, {"time": "2022-04-08 01:10:00", "val": 0.0, "median": null, "p90": null, "p10": null}, {"time": "2022-04-08 01:20:00", "val": 0.0, "median": null, "p90": null, "p10": null}, {"time": "2022-04-08 01:30:00", "val": 0.0, "median": null, "p90": null, "p10": null}, {"time": "2022-04-08 01:40:00", "val": 0.0, "median": null, "p90": null, "p10": null}, {"time": "2022-04-08 01:50:00", "val": 0.0, "median": null, "p90": null, "p10": null}, {"time": "2022-04-08 02:00:00", "val": 0.0, "median": null, "p90": null, "p10": null}, {"time": "2022-04-08 02:10:00", "val": 0.0, "median": null, "p90": null, "p10": null}, {"time": "2022-04-08 02:20:00", "val": 0.0, "median": null, "p90": null, "p10": null}, {"time": "2022-04-08 02:30:00", "val": 0.0, "median": null, "p90": null, "p10": null}, {"time": "2022-04-08 02:40:00", "val": 0.0, "median": null, "p90": null, "p10": null}, {"time": "2022-04-08 02:50:00", "val": 0.0, "median": null, "p90": null, "p10": null}, {"time": "2022-04-08 03:00:00", "val": 0.0, "median": null, "p90": null, "p10": null}, {"time": "2022-04-08 03:10:00", "val": 0.0, "median": null, "p90": null, "p10": null}, {"time": "2022-04-08 03:20:00", "val": 0.0, "median": null, "p90": null, "p10": null}, {"time": "2022-04-08 03:30:00", "val": 0.0, "median": null, "p90": null, "p10": null}, {"time": "2022-04-08 03:40:00", "val": 0.0, "median": null, "p90": null, "p10": null}, {"time": "2022-04-08 03:50:00", "val": 0.0, "median": null, "p90": null, "p10": null}, {"time": "2022-04-08 04:00:00", "val": 0.0, "median": null, "p90": null, "p10": null}, {"time": "2022-04-08 04:10:00", "val": 0.0, "median": null, "p90": null, "p10": null}, {"time": "2022-04-08 04:20:00", "val": 0.0, "median": null, "p90": null, "p10": null}, {"time": "2022-04-08 04:30:00", "val": 0.0, "median": null, "p90": null, "p10": null}, {"time": "2022-04-08 04:40:00", "val": 0.0, "median": null, "p90": null, "p10": null}, {"time": "2022-04-08 04:50:00", "val": 0.0, "median": null, "p90": null, "p10": null}, {"time": "2022-04-08 05:00:00", "val": 0.0, "median": null, "p90": null, "p10": null}, {"time": "2022-04-08 05:10:00", "val": 0.0, "median": null, "p90": null, "p10": null}, {"time": "2022-04-08 05:20:00", "val": 0.0, "median": null, "p90": null, "p10": null}, {"time": "2022-04-08 05:30:00", "val": 2.0, "median": null, "p90": null, "p10": null}, {"time": "2022-04-08 05:40:00", "val": 14.0, "median": null, "p90": null, "p10": null}, {"time": "2022-04-08 05:50:00", "val": 29.0, "median": null, "p90": null, "p10": null}, {"time": "2022-04-08 06:00:00", "val": 45.0, "median": null, "p90": null, "p10": null}, {"time": "2022-04-08 06:10:00", "val": 65.0, "median": null, "p90": null, "p10": null}, {"time": "2022-04-08 06:20:00", "val": 90.0, "median": null, "p90": null, "p10": null}, {"time": "2022-04-08 06:30:00", "val": 119.0, "median": null, "p90": null, "p10": null}, {"time": "2022-04-08 06:40:00", "val": 148.0, "median": null, "p90": null, "p10": null}, {"time": "2022-04-08 06:50:00", "val": 177.0, "median": null, "p90": null, "p10": null}, {"time": "2022-04-08 07:00:00", "val": 213.0, "median": null, "p90": null, "p10": null}, {"time": "2022-04-08 07:10:00", "val": 246.0, "median": null, "p90": null, "p10": null}, {"time": "2022-04-08 07:20:00", "val": 286.0, "median": null, "p90": null, "p10": null}, {"time": "2022-04-08 07:30:00", "val": 330.0, "median": null, "p90": null, "p10": null}, {"time": "2022-04-08 07:40:00", "val": 366.0, "median": null, "p90": null, "p10": null}, {"time": "2022-04-08 07:50:00", "val": 405.0, "median": null, "p90": null, "p10": null}, {"time": "2022-04-08 08:00:00", "val": 441.0, "median": null, "p90": null, "p10": null}, {"time": "2022-04-08 08:10:00", "val": 480.0, "median": null, "p90": null, "p10": null}, {"time": "2022-04-08 08:20:00", "val": 516.0, "median": null, "p90": null, "p10": null}, {"time": "2022-04-08 08:30:00", "val": 555.0, "median": null, "p90": null, "p10": null}, {"time": "2022-04-08 08:40:00", "val": 586.0, "median": null, "p90": null, "p10": null}, {"time": "2022-04-08 08:50:00", "val": 616.0, "median": null, "p90": null, "p10": null}, {"time": "2022-04-08 09:00:00", "val": 644.0, "median": null, "p90": null, "p10": null}, {"time": "2022-04-08 09:10:00", "val": 673.0, "median": null, "p90": null, "p10": null}, {"time": "2022-04-08 09:20:00", "val": 701.0, "median": null, "p90": null, "p10": null}, {"time": "2022-04-08 09:30:00", "val": 728.0, "median": null, "p90": null, "p10": null}, {"time": "2022-04-08 09:40:00", "val": 761.0, "median": null, "p90": null, "p10": null}, {"time": "2022-04-08 09:50:00", "val": 794.0, "median": null, "p90": null, "p10": null}, {"time": "2022-04-08 10:00:00", "val": 869.0, "median": null, "p90": null, "p10": null}, {"time": "2022-04-08 10:10:00", "val": 788.0, "median": null, "p90": null, "p10": null}, {"time": "2022-04-08 10:20:00", "val": 609.0, "median": null, "p90": null, "p10": null}, {"time": "2022-04-08 10:30:00", "val": 761.0, "median": null, "p90": null, "p10": null}, {"time": "2022-04-08 10:40:00", "val": 1012.0, "median": null, "p90": null, "p10": null}, {"time": "2022-04-08 10:50:00", "val": 681.0, "median": null, "p90": null, "p10": null}, {"time": "2022-04-08 11:00:00", "val": 678.0, "median": null, "p90": null, "p10": null}, {"time": "2022-04-08 11:10:00", "val": 760.0, "median": null, "p90": null, "p10": null}, {"time": "2022-04-08 11:20:00", "val": 787.0, "median": null, "p90": null, "p10": null}, {"time": "2022-04-08 11:30:00", "val": 865.0, "median": null, "p90": null, "p10": null}, {"time": "2022-04-08 11:40:00", "val": 657.0, "median": null, "p90": null, "p10": null}, {"time": "2022-04-08 11:50:00", "val": 855.0, "median": null, "p90": null, "p10": null}, {"time": "2022-04-08 12:00:00", "val": 912.0, "median": null, "p90": null, "p10": null}, {"time": "2022-04-08 12:10:00", "val": 946.0, "median": null, "p90": null, "p10": null}, {"time": "2022-04-08 12:20:00", "val": 916.0, "median": null, "p90": null, "p10": null}, {"time": "2022-04-08 12:30:00", "val": 830.0, "median": null, "p90": null, "p10": null}, {"time": "2022-04-08 12:40:00", "val": 828.0, "median": null, "p90": null, "p10": null}, {"time": "2022-04-08 12:50:00", "val": 738.0, "median": null, "p90": null, "p10": null}, {"time": "2022-04-08 13:00:00", "val": 586.0, "median": null, "p90": null, "p10": null}, {"time": "2022-04-08 13:10:00", "val": 506.0, "median": null, "p90": null, "p10": null}, {"time": "2022-04-08 13:20:00", "val": 647.0, "median": null, "p90": null, "p10": null}, {"time": "2022-04-08 13:30:00", "val": 509.0, "median": null, "p90": null, "p10": null}, {"time": "2022-04-08 13:40:00", "val": 457.0, "median": null, "p90": null, "p10": null}, {"time": "2022-04-08 13:50:00", "val": 439.0, "median": null, "p90": null, "p10": null}, {"time": "2022-04-08 14:00:00", "val": 698.0, "median": null, "p90": null, "p10": null}, {"time": "2022-04-08 14:10:00", "val": 551.0, "median": null, "p90": null, "p10": null}, {"time": "2022-04-08 14:20:00", "val": 775.0, "median": null, "p90": null, "p10": null}, {"time": "2022-04-08 14:30:00", "val": 451.0, "median": null, "p90": null, "p10": null}, {"time": "2022-04-08 14:40:00", "val": 360.0, "median": null, "p90": null, "p10": null}, {"time": "2022-04-08 14:50:00", "val": 369.0, "median": null, "p90": null, "p10": null}, {"time": "2022-04-08 15:00:00", "val": 348.0, "median": null, "p90": null, "p10": null}, {"time": "2022-04-08 15:10:00", "val": 338.0, "median": null, "p90": null, "p10": null}, {"time": "2022-04-08 15:20:00", "val": 258.0, "median": null, "p90": null, "p10": null}, {"time": "2022-04-08 15:30:00", "val": 226.0, "median": null, "p90": null, "p10": null}, {"time": "2022-04-08 15:40:00", "val": 215.0, "median": null, "p90": null, "p10": null}, {"time": "2022-04-08 15:50:00", "val": 186.0, "median": null, "p90": null, "p10": null}, {"time": "2022-04-08 16:00:00", "val": 154.0, "median": null, "p90": null, "p10": null}, {"time": "2022-04-08 16:10:00", "val": 130.0, "median": null, "p90": null, "p10": null}, {"time": "2022-04-08 16:20:00", "val": 103.0, "median": null, "p90": null, "p10": null}, {"time": "2022-04-08 16:30:00", "val": 99.0, "median": null, "p90": null, "p10": null}, {"time": "2022-04-08 16:40:00", "val": 107.0, "median": null, "p90": null, "p10": null}, {"time": "2022-04-08 16:50:00", "val": 99.0, "median": null, "p90": null, "p10": null}, {"time": "2022-04-08 17:00:00", "val": 84.0, "median": null, "p90": null, "p10": null}, {"time": "2022-04-08 17:10:00", "val": 79.0, "median": null, "p90": null, "p10": null}, {"time": "2022-04-08 17:20:00", "val": 73.0, "median": null, "p90": null, "p10": null}, {"time": "2022-04-08 17:30:00", "val": 58.0, "median": null, "p90": null, "p10": null}, {"time": "2022-04-08 17:40:00", "val": 31.0, "median": null, "p90": null, "p10": null}, {"time": "2022-04-08 17:50:00", "val": 16.0, "median": null, "p90": null, "p10": null}, {"time": "2022-04-08 18:00:00", "val": 5.0, "median": null, "p90": null, "p10": null}, {"time": "2022-04-08 18:10:00", "val": 0.0, "median": null, "p90": null, "p10": null}, {"time": "2022-04-08 18:20:00", "val": 0.0, "median": null, "p90": null, "p10": null}, {"time": "2022-04-08 18:30:00", "val": 0.0, "median": null, "p90": null, "p10": null}, {"time": "2022-04-08 18:40:00", "val": 0.0, "median": null, "p90": null, "p10": null}, {"time": "2022-04-08 18:50:00", "val": 0.0, "median": null, "p90": null, "p10": null}, {"time": "2022-04-08 19:00:00", "val": 0.0, "median": null, "p90": null, "p10": null}, {"time": "2022-04-08 19:10:00", "val": 0.0, "median": null, "p90": null, "p10": null}, {"time": "2022-04-08 19:20:00", "val": 0.0, "median": null, "p90": null, "p10": null}, {"time": "2022-04-08 19:30:00", "val": 0.0, "median": null, "p90": null, "p10": null}, {"time": "2022-04-08 19:40:00", "val": 0.0, "median": null, "p90": null, "p10": null}, {"time": "2022-04-08 19:50:00", "val": 0.0, "median": null, "p90": null, "p10": null}, {"time": "2022-04-08 20:00:00", "val": 0.0, "median": null, "p90": null, "p10": null}, {"time": "2022-04-08 20:10:00", "val": 0.0, "median": null, "p90": null, "p10": null}, {"time": "2022-04-08 20:20:00", "val": 0.0, "median": null, "p90": null, "p10": null}, {"time": "2022-04-08 20:30:00", "val": 0.0, "median": null, "p90": null, "p10": null}, {"time": "2022-04-08 20:40:00", "val": 0.0, "median": null, "p90": null, "p10": null}, {"time": "2022-04-08 20:50:00", "val": 0.0, "median": null, "p90": null, "p10": null}, {"time": "2022-04-08 21:00:00", "val": 0.0, "median": null, "p90": null, "p10": null}, {"time": "2022-04-08 21:10:00", "val": 0.0, "median": null, "p90": null, "p10": null}, {"time": "2022-04-08 21:20:00", "val": 0.0, "median": null, "p90": null, "p10": null}, {"time": "2022-04-08 21:30:00", "val": 0.0, "median": null, "p90": null, "p10": null}, {"time": "2022-04-08 21:40:00", "val": 0.0, "median": null, "p90": null, "p10": null}, {"time": "2022-04-08 21:50:00", "val": 0.0, "median": null, "p90": null, "p10": null}, {"time": "2022-04-08 22:00:00", "val": 0.0, "median": null, "p90": null, "p10": null}, {"time": "2022-04-08 22:10:00", "val": 0.0, "median": null, "p90": null, "p10": null}, {"time": "2022-04-08 22:20:00", "val": 0.0, "median": null, "p90": null, "p10": null}, {"time": "2022-04-08 22:30:00", "val": 0.0, "median": null, "p90": null, "p10": null}, {"time": "2022-04-08 22:40:00", "val": 0.0, "median": null, "p90": null, "p10": null}, {"time": "2022-04-08 22:50:00", "val": 0.0, "median": null, "p90": null, "p10": null}, {"time": "2022-04-08 23:00:00", "val": 0.0, "median": null, "p90": null, "p10": null}, {"time": "2022-04-08 23:10:00", "val": 0.0, "median": null, "p90": null, "p10": null}, {"time": "2022-04-08 23:20:00", "val": 0.0, "median": null, "p90": null, "p10": null}, {"time": "2022-04-08 23:30:00", "val": 0.0, "median": null, "p90": null, "p10": null}, {"time": "2022-04-08 23:40:00", "val": 0.0, "median": null, "p90": null, "p10": null}, {"time": "2022-04-08 23:50:00", "val": 0.0, "median": null, "p90": null, "p10": null}, {"time": "2022-04-09 00:00:00", "val": 0.0, "median": null, "p90": null, "p10": null}, {"time": "2022-04-09 00:10:00", "val": 0.0, "median": null, "p90": null, "p10": null}, {"time": "2022-04-09 00:20:00", "val": 0.0, "median": null, "p90": null, "p10": null}, {"time": "2022-04-09 00:30:00", "val": 0.0, "median": null, "p90": null, "p10": null}, {"time": "2022-04-09 00:40:00", "val": 0.0, "median": null, "p90": null, "p10": null}, {"time": "2022-04-09 00:50:00", "val": 0.0, "median": null, "p90": null, "p10": null}, {"time": "2022-04-09 01:00:00", "val": 0.0, "median": null, "p90": null, "p10": null}, {"time": "2022-04-09 01:10:00", "val": 0.0, "median": null, "p90": null, "p10": null}, {"time": "2022-04-09 01:20:00", "val": 0.0, "median": null, "p90": null, "p10": null}, {"time": "2022-04-09 01:30:00", "val": 0.0, "median": null, "p90": null, "p10": null}, {"time": "2022-04-09 01:40:00", "val": 0.0, "median": null, "p90": null, "p10": null}, {"time": "2022-04-09 01:50:00", "val": 0.0, "median": null, "p90": null, "p10": null}, {"time": "2022-04-09 02:00:00", "val": 0.0, "median": null, "p90": null, "p10": null}, {"time": "2022-04-09 02:10:00", "val": 0.0, "median": null, "p90": null, "p10": null}, {"time": "2022-04-09 02:20:00", "val": 0.0, "median": null, "p90": null, "p10": null}, {"time": "2022-04-09 02:30:00", "val": 0.0, "median": null, "p90": null, "p10": null}, {"time": "2022-04-09 02:40:00", "val": 0.0, "median": null, "p90": null, "p10": null}, {"time": "2022-04-09 02:50:00", "val": 0.0, "median": null, "p90": null, "p10": null}, {"time": "2022-04-09 03:00:00", "val": 0.0, "median": null, "p90": null, "p10": null}, {"time": "2022-04-09 03:10:00", "val": 0.0, "median": null, "p90": null, "p10": null}, {"time": "2022-04-09 03:20:00", "val": 0.0, "median": null, "p90": null, "p10": null}, {"time": "2022-04-09 03:40:00", "val": 0.0, "median": null, "p90": null, "p10": null}, {"time": "2022-04-09 03:50:00", "val": 0.0, "median": null, "p90": null, "p10": null}, {"time": "2022-04-09 04:00:00", "val": 0.0, "median": null, "p90": null, "p10": null}, {"time": "2022-04-09 04:10:00", "val": 0.0, "median": null, "p90": null, "p10": null}, {"time": "2022-04-09 04:20:00", "val": 0.0, "median": null, "p90": null, "p10": null}, {"time": "2022-04-09 04:30:00", "val": 0.0, "median": null, "p90": null, "p10": null}, {"time": "2022-04-09 04:40:00", "val": 0.0, "median": null, "p90": null, "p10": null}, {"time": "2022-04-09 04:50:00", "val": 0.0, "median": null, "p90": null, "p10": null}, {"time": "2022-04-09 05:00:00", "val": 0.0, "median": null, "p90": null, "p10": null}, {"time": "2022-04-09 05:10:00", "val": 0.0, "median": null, "p90": null, "p10": null}, {"time": "2022-04-09 05:20:00", "val": 0.0, "median": null, "p90": null, "p10": null}, {"time": "2022-04-09 05:30:00", "val": 4.0, "median": null, "p90": null, "p10": null}, {"time": "2022-04-09 05:40:00", "val": 13.0, "median": null, "p90": null, "p10": null}, {"time": "2022-04-09 05:50:00", "val": 42.0, "median": null, "p90": null, "p10": null}, {"time": "2022-04-09 06:00:00", "val": 76.0, "median": null, "p90": null, "p10": null}, {"time": "2022-04-09 06:10:00", "val": 112.0, "median": null, "p90": null, "p10": null}, {"time": "2022-04-09 06:20:00", "val": 147.0, "median": null, "p90": null, "p10": null}, {"time": "2022-04-09 06:30:00", "val": 184.0, "median": null, "p90": null, "p10": null}, {"time": "2022-04-09 06:40:00", "val": 224.0, "median": null, "p90": null, "p10": null}, {"time": "2022-04-09 06:50:00", "val": 271.0, "median": null, "p90": null, "p10": null}, {"time": "2022-04-09 07:00:00", "val": 319.0, "median": null, "p90": null, "p10": null}, {"time": "2022-04-09 07:10:00", "val": 361.0, "median": null, "p90": null, "p10": null}, {"time": "2022-04-09 07:20:00", "val": 402.0, "median": null, "p90": null, "p10": null}, {"time": "2022-04-09 07:30:00", "val": 445.0, "median": null, "p90": null, "p10": null}, {"time": "2022-04-09 07:40:00", "val": 486.0, "median": null, "p90": null, "p10": null}, {"time": "2022-04-09 07:50:00", "val": 527.0, "median": null, "p90": null, "p10": null}, {"time": "2022-04-09 08:00:00", "val": 567.0, "median": null, "p90": null, "p10": null}, {"time": "2022-04-09 08:10:00", "val": 605.0, "median": null, "p90": null, "p10": null}, {"time": "2022-04-09 08:20:00", "val": null, "median": 516.0, "p90": 574.0, "p10": 406.4}, {"time": "2022-04-09 08:30:00", "val": null, "median": 548.0, "p90": 610.0, "p10": 456.0}, {"time": "2022-04-09 08:40:00", "val": null, "median": 579.0, "p90": 644.0, "p10": 467.0}, {"time": "2022-04-09 08:50:00", "val": null, "median": 616.0, "p90": 680.0, "p10": 524.0}, {"time": "2022-04-09 09:00:00", "val": null, "median": 653.0, "p90": 715.0, "p10": 502.0}, {"time": "2022-04-09 09:10:00", "val": null, "median": 673.0, "p90": 746.0, "p10": 515.0}, {"time": "2022-04-09 09:20:00", "val": null, "median": 700.0, "p90": 773.0, "p10": 532.0}, {"time": "2022-04-09 09:30:00", "val": null, "median": 728.0, "p90": 802.0, "p10": 563.0}, {"time": "2022-04-09 09:40:00", "val": null, "median": 761.0, "p90": 829.0, "p10": 608.0}, {"time": "2022-04-09 09:50:00", "val": null, "median": 794.0, "p90": 859.0, "p10": 655.0}, {"time": "2022-04-09 10:00:00", "val": null, "median": 803.0, "p90": 884.0, "p10": 600.0}, {"time": "2022-04-09 10:10:00", "val": null, "median": 825.0, "p90": 904.0, "p10": 524.0}, {"time": "2022-04-09 10:20:00", "val": null, "median": 846.0, "p90": 919.0, "p10": 609.0}, {"time": "2022-04-09 10:30:00", "val": null, "median": 864.0, "p90": 941.0, "p10": 645.0}, {"time": "2022-04-09 10:40:00", "val": null, "median": 880.0, "p90": 1012.0, "p10": 728.0}, {"time": "2022-04-09 10:50:00", "val": null, "median": 903.0, "p90": 963.0, "p10": 736.0}, {"time": "2022-04-09 11:00:00", "val": null, "median": 924.0, "p90": 969.0, "p10": 776.1}, {"time": "2022-04-09 11:10:00", "val": null, "median": 910.0, "p90": 978.0, "p10": 760.0}, {"time": "2022-04-09 11:20:00", "val": null, "median": 912.0, "p90": 983.0, "p10": 787.0}, {"time": "2022-04-09 11:30:00", "val": null, "median": 917.0, "p90": 990.0, "p10": 793.0}, {"time": "2022-04-09 11:40:00", "val": null, "median": 929.0, "p90": 994.0, "p10": 667.8}, {"time": "2022-04-09 11:50:00", "val": null, "median": 923.0, "p90": 959.5, "p10": 586.0}, {"time": "2022-04-09 12:00:00", "val": null, "median": 912.0, "p90": 992.0, "p10": 703.0}, {"time": "2022-04-09 12:10:00", "val": null, "median": 916.0, "p90": 982.0, "p10": 781.0}, {"time": "2022-04-09 12:20:00", "val": null, "median": 890.0, "p90": 958.0, "p10": 769.0}, {"time": "2022-04-09 12:30:00", "val": null, "median": 893.0, "p90": 969.0, "p10": 826.0}, {"time": "2022-04-09 12:40:00", "val": null, "median": 873.0, "p90": 943.4, "p10": 774.0}, {"time": "2022-04-09 12:50:00", "val": null, "median": 857.0, "p90": 934.0, "p10": 648.0}, {"time": "2022-04-09 13:00:00", "val": null, "median": 834.0, "p90": 915.0, "p10": 586.0}, {"time": "2022-04-09 13:10:00", "val": null, "median": 810.0, "p90": 893.0, "p10": 506.0}, {"time": "2022-04-09 13:20:00", "val": null, "median": 808.0, "p90": 872.5, "p10": 608.0}, {"time": "2022-04-09 13:30:00", "val": null, "median": 811.0, "p90": 859.0, "p10": 509.0}, {"time": "2022-04-09 13:40:00", "val": null, "median": 785.0, "p90": 845.0, "p10": 457.0}, {"time": "2022-04-09 13:50:00", "val": null, "median": 773.0, "p90": 825.0, "p10": 524.0}, {"time": "2022-04-09 14:00:00", "val": null, "median": 738.0, "p90": 798.7, "p10": 623.0}, {"time": "2022-04-09 14:10:00", "val": null, "median": 719.0, "p90": 777.0, "p10": 555.0}, {"time": "2022-04-09 14:20:00", "val": null, "median": 689.0, "p90": 775.0, "p10": 541.0}, {"time": "2022-04-09 14:30:00", "val": null, "median": 643.0, "p90": 728.0, "p10": 451.0}, {"time": "2022-04-09 14:40:00", "val": null, "median": 624.0, "p90": 693.0, "p10": 360.0}, {"time": "2022-04-09 14:50:00", "val": null, "median": 566.0, "p90": 671.0, "p10": 369.0}, {"time": "2022-04-09 15:00:00", "val": null, "median": 582.0, "p90": 644.0, "p10": 444.0}, {"time": "2022-04-09 15:10:00", "val": null, "median": 525.0, "p90": 611.0, "p10": 365.0}, {"time": "2022-04-09 15:20:00", "val": null, "median": 518.0, "p90": 557.0, "p10": 312.0}, {"time": "2022-04-09 15:30:00", "val": null, "median": 480.0, "p90": 524.0, "p10": 226.0}, {"time": "2022-04-09 15:40:00", "val": null, "median": 446.0, "p90": 496.0, "p10": 215.0}, {"time": "2022-04-09 15:50:00", "val": null, "median": 393.5, "p90": 461.0, "p10": 186.0}, {"time": "2022-04-09 16:00:00", "val": null, "median": 325.0, "p90": 430.0, "p10": 160.0}, {"time": "2022-04-09 16:10:00", "val": null, "median": 327.0, "p90": 385.0, "p10": 177.0}, {"time": "2022-04-09 16:20:00", "val": null, "median": 286.0, "p90": 344.0, "p10": 136.0}, {"time": "2022-04-09 16:30:00", "val": null, "median": 245.0, "p90": 299.0, "p10": 119.0}, {"time": "2022-04-09 16:40:00", "val": null, "median": 202.5, "p90": 257.0, "p10": 107.0}, {"time": "2022-04-09 16:50:00", "val": null, "median": 141.5, "p90": 210.0, "p10": 80.0}, {"time": "2022-04-09 17:00:00", "val": null, "median": 125.0, "p90": 168.0, "p10": 73.0}, {"time": "2022-04-09 17:10:00", "val": null, "median": 90.0, "p90": 124.0, "p10": 66.0}, {"time": "2022-04-09 17:20:00", "val": null, "median": 67.0, "p90": 85.0, "p10": 50.0}, {"time": "2022-04-09 17:30:00", "val": null, "median": 36.0, "p90": 58.0, "p10": 28.0}, {"time": "2022-04-09 17:40:00", "val": null, "median": 23.0, "p90": 31.0, "p10": 15.0}, {"time": "2022-04-09 17:50:00", "val": null, "median": 11.0, "p90": 15.0, "p10": 6.0}, {"time": "2022-04-09 18:00:00", "val": null, "median": 1.0, "p90": 4.0, "p10": 0.0}, {"time": "2022-04-09 18:10:00", "val": null, "median": 0.0, "p90": 0.0, "p10": 0.0}, {"time": "2022-04-09 18:20:00", "val": null, "median": 0.0, "p90": 0.0, "p10": 0.0}, {"time": "2022-04-09 18:30:00", "val": null, "median": 0.0, "p90": 0.0, "p10": 0.0}, {"time": "2022-04-09 18:40:00", "val": null, "median": 0.0, "p90": 0.0, "p10": 0.0}, {"time": "2022-04-09 18:50:00", "val": null, "median": 0.0, "p90": 0.0, "p10": 0.0}, {"time": "2022-04-09 19:00:00", "val": null, "median": 0.0, "p90": 0.0, "p10": 0.0}, {"time": "2022-04-09 19:10:00", "val": null, "median": 0.0, "p90": 0.0, "p10": 0.0}, {"time": "2022-04-09 19:20:00", "val": null, "median": 0.0, "p90": 0.0, "p10": 0.0}, {"time": "2022-04-09 19:30:00", "val": null, "median": 0.0, "p90": 0.0, "p10": 0.0}, {"time": "2022-04-09 19:40:00", "val": null, "median": 0.0, "p90": 0.0, "p10": 0.0}, {"time": "2022-04-09 19:50:00", "val": null, "median": 0.0, "p90": 0.0, "p10": 0.0}, {"time": "2022-04-09 20:00:00", "val": null, "median": 0.0, "p90": 0.0, "p10": 0.0}, {"time": "2022-04-09 20:10:00", "val": null, "median": 0.0, "p90": 0.0, "p10": 0.0}, {"time": "2022-04-09 20:20:00", "val": null, "median": 0.0, "p90": 0.0, "p10": 0.0}, {"time": "2022-04-09 20:30:00", "val": null, "median": 0.0, "p90": 0.0, "p10": 0.0}, {"time": "2022-04-09 20:40:00", "val": null, "median": 0.0, "p90": 0.0, "p10": 0.0}, {"time": "2022-04-09 20:50:00", "val": null, "median": 0.0, "p90": 0.0, "p10": 0.0}, {"time": "2022-04-09 21:00:00", "val": null, "median": 0.0, "p90": 0.0, "p10": 0.0}, {"time": "2022-04-09 21:10:00", "val": null, "median": 0.0, "p90": 0.0, "p10": 0.0}, {"time": "2022-04-09 21:20:00", "val": null, "median": 0.0, "p90": 0.0, "p10": 0.0}, {"time": "2022-04-09 21:30:00", "val": null, "median": 0.0, "p90": 0.0, "p10": 0.0}, {"time": "2022-04-09 21:40:00", "val": null, "median": 0.0, "p90": 0.0, "p10": 0.0}, {"time": "2022-04-09 21:50:00", "val": null, "median": 0.0, "p90": 0.0, "p10": 0.0}, {"time": "2022-04-09 22:00:00", "val": null, "median": 0.0, "p90": 0.0, "p10": 0.0}, {"time": "2022-04-09 22:10:00", "val": null, "median": 0.0, "p90": 0.0, "p10": 0.0}, {"time": "2022-04-09 22:20:00", "val": null, "median": 0.0, "p90": 0.0, "p10": 0.0}, {"time": "2022-04-09 22:30:00", "val": null, "median": 0.0, "p90": 0.0, "p10": 0.0}, {"time": "2022-04-09 22:40:00", "val": null, "median": 0.0, "p90": 0.0, "p10": 0.0}, {"time": "2022-04-09 22:50:00", "val": null, "median": 0.0, "p90": 0.0, "p10": 0.0}, {"time": "2022-04-09 23:00:00", "val": null, "median": 0.0, "p90": 0.0, "p10": 0.0}, {"time": "2022-04-09 23:10:00", "val": null, "median": 0.0, "p90": 0.0, "p10": 0.0}, {"time": "2022-04-09 23:20:00", "val": null, "median": 0.0, "p90": 0.0, "p10": 0.0}, {"time": "2022-04-09 23:30:00", "val": null, "median": 0.0, "p90": 0.0, "p10": 0.0}, {"time": "2022-04-09 23:40:00", "val": null, "median": 0.0, "p90": 0.0, "p10": 0.0}, {"time": "2022-04-09 23:50:00", "val": null, "median": 0.0, "p90": 0.0, "p10": 0.0}, {"time": "2022-04-10 00:00:00", "val": null, "median": 0.0, "p90": 0.0, "p10": 0.0}, {"time": "2022-04-10 00:10:00", "val": null, "median": 0.0, "p90": 0.0, "p10": 0.0}, {"time": "2022-04-10 00:20:00", "val": null, "median": 0.0, "p90": 0.0, "p10": 0.0}, {"time": "2022-04-10 00:30:00", "val": null, "median": 0.0, "p90": 0.0, "p10": 0.0}, {"time": "2022-04-10 00:40:00", "val": null, "median": 0.0, "p90": 0.0, "p10": 0.0}, {"time": "2022-04-10 00:50:00", "val": null, "median": 0.0, "p90": 0.0, "p10": 0.0}, {"time": "2022-04-10 01:00:00", "val": null, "median": 0.0, "p90": 0.0, "p10": 0.0}, {"time": "2022-04-10 01:10:00", "val": null, "median": 0.0, "p90": 0.0, "p10": 0.0}, {"time": "2022-04-10 01:20:00", "val": null, "median": 0.0, "p90": 0.0, "p10": 0.0}, {"time": "2022-04-10 01:30:00", "val": null, "median": 0.0, "p90": 0.0, "p10": 0.0}, {"time": "2022-04-10 01:40:00", "val": null, "median": 0.0, "p90": 0.0, "p10": 0.0}, {"time": "2022-04-10 01:50:00", "val": null, "median": 0.0, "p90": 0.0, "p10": 0.0}, {"time": "2022-04-10 02:00:00", "val": null, "median": 0.0, "p90": 0.0, "p10": 0.0}, {"time": "2022-04-10 02:10:00", "val": null, "median": 0.0, "p90": 0.0, "p10": 0.0}, {"time": "2022-04-10 02:20:00", "val": null, "median": 0.0, "p90": 0.0, "p10": 0.0}, {"time": "2022-04-10 02:30:00", "val": null, "median": 0.0, "p90": 0.0, "p10": 0.0}, {"time": "2022-04-10 02:40:00", "val": null, "median": 0.0, "p90": 0.0, "p10": 0.0}, {"time": "2022-04-10 02:50:00", "val": null, "median": 0.0, "p90": 0.0, "p10": 0.0}, {"time": "2022-04-10 03:00:00", "val": null, "median": 0.0, "p90": 0.0, "p10": 0.0}, {"time": "2022-04-10 03:10:00", "val": null, "median": 0.0, "p90": 0.0, "p10": 0.0}, {"time": "2022-04-10 03:20:00", "val": null, "median": 0.0, "p90": 0.0, "p10": 0.0}, {"time": "2022-04-10 03:30:00", "val": null, "median": 0.0, "p90": 0.0, "p10": 0.0}, {"time": "2022-04-10 03:40:00", "val": null, "median": 0.0, "p90": 0.0, "p10": 0.0}, {"time": "2022-04-10 03:50:00", "val": null, "median": 0.0, "p90": 0.0, "p10": 0.0}, {"time": "2022-04-10 04:00:00", "val": null, "median": 0.0, "p90": 0.0, "p10": 0.0}, {"time": "2022-04-10 04:10:00", "val": null, "median": 0.0, "p90": 0.0, "p10": 0.0}, {"time": "2022-04-10 04:20:00", "val": null, "median": 0.0, "p90": 0.0, "p10": 0.0}, {"time": "2022-04-10 04:30:00", "val": null, "median": 0.0, "p90": 0.0, "p10": 0.0}, {"time": "2022-04-10 04:40:00", "val": null, "median": 0.0, "p90": 0.0, "p10": 0.0}, {"time": "2022-04-10 04:50:00", "val": null, "median": 0.0, "p90": 0.0, "p10": 0.0}, {"time": "2022-04-10 05:00:00", "val": null, "median": 0.0, "p90": 0.0, "p10": 0.0}, {"time": "2022-04-10 05:10:00", "val": null, "median": 0.0, "p90": 0.0, "p10": 0.0}, {"time": "2022-04-10 05:20:00", "val": null, "median": 0.0, "p90": 0.0, "p10": 0.0}, {"time": "2022-04-10 05:30:00", "val": null, "median": 0.0, "p90": 2.0, "p10": 0.0}, {"time": "2022-04-10 05:40:00", "val": null, "median": 4.0, "p90": 13.0, "p10": 0.0}, {"time": "2022-04-10 05:50:00", "val": null, "median": 15.0, "p90": 30.0, "p10": 4.0}, {"time": "2022-04-10 06:00:00", "val": null, "median": 33.0, "p90": 49.0, "p10": 14.0}, {"time": "2022-04-10 06:10:00", "val": null, "median": 60.0, "p90": 77.0, "p10": 27.6}, {"time": "2022-04-10 06:20:00", "val": null, "median": 90.0, "p90": 120.0, "p10": 49.0}, {"time": "2022-04-10 06:30:00", "val": null, "median": 119.0, "p90": 172.0, "p10": 75.0}, {"time": "2022-04-10 06:40:00", "val": null, "median": 148.0, "p90": 223.0, "p10": 101.0}, {"time": "2022-04-10 06:50:00", "val": null, "median": 179.0, "p90": 235.0, "p10": 135.0}, {"time": "2022-04-10 07:00:00", "val": null, "median": 225.0, "p90": 271.0, "p10": 170.0}, {"time": "2022-04-10 07:10:00", "val": null, "median": 249.0, "p90": 318.0, "p10": 206.0}, {"time": "2022-04-10 07:20:00", "val": null, "median": 289.0, "p90": 360.0, "p10": 218.8}, {"time": "2022-04-10 07:30:00", "val": null, "median": 330.0, "p90": 401.0, "p10": 271.2}, {"time": "2022-04-10 07:40:00", "val": null, "median": 368.0, "p90": 443.0, "p10": 315.0}, {"time": "2022-04-10 07:50:00", "val": null, "median": 406.0, "p90": 479.0, "p10": 337.0}, {"time": "2022-04-10 08:00:00", "val": null, "median": 462.0, "p90": 524.0, "p10": 369.0}, {"time": "2022-04-10 08:10:00", "val": null, "median": 487.0, "p90": 551.0, "p10": 416.0}, {"time": "2022-04-10 08:20:00", "val": null, "median": 516.0, "p90": 574.0, "p10": 406.4}, {"time": "2022-04-10 08:30:00", "val": null, "median": 548.0, "p90": 610.0, "p10": 456.0}, {"time": "2022-04-10 08:40:00", "val": null, "median": 579.0, "p90": 644.0, "p10": 467.0}, {"time": "2022-04-10 08:50:00", "val": null, "median": 616.0, "p90": 680.0, "p10": 524.0}, {"time": "2022-04-10 09:00:00", "val": null, "median": 653.0, "p90": 715.0, "p10": 502.0}, {"time": "2022-04-10 09:10:00", "val": null, "median": 673.0, "p90": 746.0, "p10": 515.0}, {"time": "2022-04-10 09:20:00", "val": null, "median": 700.0, "p90": 773.0, "p10": 532.0}, {"time": "2022-04-10 09:30:00", "val": null, "median": 728.0, "p90": 802.0, "p10": 563.0}, {"time": "2022-04-10 09:40:00", "val": null, "median": 761.0, "p90": 829.0, "p10": 608.0}, {"time": "2022-04-10 09:50:00", "val": null, "median": 794.0, "p90": 859.0, "p10": 655.0}, {"time": "2022-04-10 10:00:00", "val": null, "median": 803.0, "p90": 884.0, "p10": 600.0}, {"time": "2022-04-10 10:10:00", "val": null, "median": 825.0, "p90": 904.0, "p10": 524.0}, {"time": "2022-04-10 10:20:00", "val": null, "median": 846.0, "p90": 919.0, "p10": 609.0}, {"time": "2022-04-10 10:30:00", "val": null, "median": 864.0, "p90": 941.0, "p10": 645.0}, {"time": "2022-04-10 10:40:00", "val": null, "median": 880.0, "p90": 1012.0, "p10": 728.0}, {"time": "2022-04-10 10:50:00", "val": null, "median": 903.0, "p90": 963.0, "p10": 736.0}, {"time": "2022-04-10 11:00:00", "val": null, "median": 924.0, "p90": 969.0, "p10": 776.1}, {"time": "2022-04-10 11:10:00", "val": null, "median": 910.0, "p90": 978.0, "p10": 760.0}, {"time": "2022-04-10 11:20:00", "val": null, "median": 912.0, "p90": 983.0, "p10": 787.0}, {"time": "2022-04-10 11:30:00", "val": null, "median": 917.0, "p90": 990.0, "p10": 793.0}, {"time": "2022-04-10 11:40:00", "val": null, "median": 929.0, "p90": 994.0, "p10": 667.8}, {"time": "2022-04-10 11:50:00", "val": null, "median": 923.0, "p90": 959.5, "p10": 586.0}, {"time": "2022-04-10 12:00:00", "val": null, "median": 912.0, "p90": 992.0, "p10": 703.0}, {"time": "2022-04-10 12:10:00", "val": null, "median": 916.0, "p90": 982.0, "p10": 781.0}, {"time": "2022-04-10 12:20:00", "val": null, "median": 890.0, "p90": 958.0, "p10": 769.0}, {"time": "2022-04-10 12:30:00", "val": null, "median": 893.0, "p90": 969.0, "p10": 826.0}, {"time": "2022-04-10 12:40:00", "val": null, "median": 873.0, "p90": 943.4, "p10": 774.0}, {"time": "2022-04-10 12:50:00", "val": null, "median": 857.0, "p90": 934.0, "p10": 648.0}, {"time": "2022-04-10 13:00:00", "val": null, "median": 834.0, "p90": 915.0, "p10": 586.0}, {"time": "2022-04-10 13:10:00", "val": null, "median": 810.0, "p90": 893.0, "p10": 506.0}, {"time": "2022-04-10 13:20:00", "val": null, "median": 808.0, "p90": 872.5, "p10": 608.0}, {"time": "2022-04-10 13:30:00", "val": null, "median": 811.0, "p90": 859.0, "p10": 509.0}, {"time": "2022-04-10 13:40:00", "val": null, "median": 785.0, "p90": 845.0, "p10": 457.0}, {"time": "2022-04-10 13:50:00", "val": null, "median": 773.0, "p90": 825.0, "p10": 524.0}, {"time": "2022-04-10 14:00:00", "val": null, "median": 738.0, "p90": 798.7, "p10": 623.0}, {"time": "2022-04-10 14:10:00", "val": null, "median": 719.0, "p90": 777.0, "p10": 555.0}, {"time": "2022-04-10 14:20:00", "val": null, "median": 689.0, "p90": 775.0, "p10": 541.0}, {"time": "2022-04-10 14:30:00", "val": null, "median": 643.0, "p90": 728.0, "p10": 451.0}, {"time": "2022-04-10 14:40:00", "val": null, "median": 624.0, "p90": 693.0, "p10": 360.0}, {"time": "2022-04-10 14:50:00", "val": null, "median": 566.0, "p90": 671.0, "p10": 369.0}, {"time": "2022-04-10 15:00:00", "val": null, "median": 582.0, "p90": 644.0, "p10": 444.0}, {"time": "2022-04-10 15:10:00", "val": null, "median": 525.0, "p90": 611.0, "p10": 365.0}, {"time": "2022-04-10 15:20:00", "val": null, "median": 518.0, "p90": 557.0, "p10": 312.0}, {"time": "2022-04-10 15:30:00", "val": null, "median": 480.0, "p90": 524.0, "p10": 226.0}, {"time": "2022-04-10 15:40:00", "val": null, "median": 446.0, "p90": 496.0, "p10": 215.0}, {"time": "2022-04-10 15:50:00", "val": null, "median": 393.5, "p90": 461.0, "p10": 186.0}, {"time": "2022-04-10 16:00:00", "val": null, "median": 325.0, "p90": 430.0, "p10": 160.0}, {"time": "2022-04-10 16:10:00", "val": null, "median": 327.0, "p90": 385.0, "p10": 177.0}, {"time": "2022-04-10 16:20:00", "val": null, "median": 286.0, "p90": 344.0, "p10": 136.0}, {"time": "2022-04-10 16:30:00", "val": null, "median": 245.0, "p90": 299.0, "p10": 119.0}, {"time": "2022-04-10 16:40:00", "val": null, "median": 202.5, "p90": 257.0, "p10": 107.0}, {"time": "2022-04-10 16:50:00", "val": null, "median": 141.5, "p90": 210.0, "p10": 80.0}, {"time": "2022-04-10 17:00:00", "val": null, "median": 125.0, "p90": 168.0, "p10": 73.0}, {"time": "2022-04-10 17:10:00", "val": null, "median": 90.0, "p90": 124.0, "p10": 66.0}, {"time": "2022-04-10 17:20:00", "val": null, "median": 67.0, "p90": 85.0, "p10": 50.0}, {"time": "2022-04-10 17:30:00", "val": null, "median": 36.0, "p90": 58.0, "p10": 28.0}, {"time": "2022-04-10 17:40:00", "val": null, "median": 23.0, "p90": 31.0, "p10": 15.0}, {"time": "2022-04-10 17:50:00", "val": null, "median": 11.0, "p90": 15.0, "p10": 6.0}, {"time": "2022-04-10 18:00:00", "val": null, "median": 1.0, "p90": 4.0, "p10": 0.0}, {"time": "2022-04-10 18:10:00", "val": null, "median": 0.0, "p90": 0.0, "p10": 0.0}, {"time": "2022-04-10 18:20:00", "val": null, "median": 0.0, "p90": 0.0, "p10": 0.0}, {"time": "2022-04-10 18:30:00", "val": null, "median": 0.0, "p90": 0.0, "p10": 0.0}, {"time": "2022-04-10 18:40:00", "val": null, "median": 0.0, "p90": 0.0, "p10": 0.0}, {"time": "2022-04-10 18:50:00", "val": null, "median": 0.0, "p90": 0.0, "p10": 0.0}, {"time": "2022-04-10 19:00:00", "val": null, "median": 0.0, "p90": 0.0, "p10": 0.0}, {"time": "2022-04-10 19:10:00", "val": null, "median": 0.0, "p90": 0.0, "p10": 0.0}, {"time": "2022-04-10 19:20:00", "val": null, "median": 0.0, "p90": 0.0, "p10": 0.0}, {"time": "2022-04-10 19:30:00", "val": null, "median": 0.0, "p90": 0.0, "p10": 0.0}, {"time": "2022-04-10 19:40:00", "val": null, "median": 0.0, "p90": 0.0, "p10": 0.0}, {"time": "2022-04-10 19:50:00", "val": null, "median": 0.0, "p90": 0.0, "p10": 0.0}, {"time": "2022-04-10 20:00:00", "val": null, "median": 0.0, "p90": 0.0, "p10": 0.0}, {"time": "2022-04-10 20:10:00", "val": null, "median": 0.0, "p90": 0.0, "p10": 0.0}, {"time": "2022-04-10 20:20:00", "val": null, "median": 0.0, "p90": 0.0, "p10": 0.0}, {"time": "2022-04-10 20:30:00", "val": null, "median": 0.0, "p90": 0.0, "p10": 0.0}, {"time": "2022-04-10 20:40:00", "val": null, "median": 0.0, "p90": 0.0, "p10": 0.0}, {"time": "2022-04-10 20:50:00", "val": null, "median": 0.0, "p90": 0.0, "p10": 0.0}, {"time": "2022-04-10 21:00:00", "val": null, "median": 0.0, "p90": 0.0, "p10": 0.0}, {"time": "2022-04-10 21:10:00", "val": null, "median": 0.0, "p90": 0.0, "p10": 0.0}, {"time": "2022-04-10 21:20:00", "val": null, "median": 0.0, "p90": 0.0, "p10": 0.0}, {"time": "2022-04-10 21:30:00", "val": null, "median": 0.0, "p90": 0.0, "p10": 0.0}, {"time": "2022-04-10 21:40:00", "val": null, "median": 0.0, "p90": 0.0, "p10": 0.0}, {"time": "2022-04-10 21:50:00", "val": null, "median": 0.0, "p90": 0.0, "p10": 0.0}, {"time": "2022-04-10 22:00:00", "val": null, "median": 0.0, "p90": 0.0, "p10": 0.0}, {"time": "2022-04-10 22:10:00", "val": null, "median": 0.0, "p90": 0.0, "p10": 0.0}, {"time": "2022-04-10 22:20:00", "val": null, "median": 0.0, "p90": 0.0, "p10": 0.0}, {"time": "2022-04-10 22:30:00", "val": null, "median": 0.0, "p90": 0.0, "p10": 0.0}, {"time": "2022-04-10 22:40:00", "val": null, "median": 0.0, "p90": 0.0, "p10": 0.0}, {"time": "2022-04-10 22:50:00", "val": null, "median": 0.0, "p90": 0.0, "p10": 0.0}, {"time": "2022-04-10 23:00:00", "val": null, "median": 0.0, "p90": 0.0, "p10": 0.0}, {"time": "2022-04-10 23:10:00", "val": null, "median": 0.0, "p90": 0.0, "p10": 0.0}, {"time": "2022-04-10 23:20:00", "val": null, "median": 0.0, "p90": 0.0, "p10": 0.0}, {"time": "2022-04-10 23:30:00", "val": null, "median": 0.0, "p90": 0.0, "p10": 0.0}, {"time": "2022-04-10 23:40:00", "val": null, "median": 0.0, "p90": 0.0, "p10": 0.0}, {"time": "2022-04-10 23:50:00", "val": null, "median": 0.0, "p90": 0.0, "p10": 0.0}, {"time": "2022-04-11 00:00:00", "val": null, "median": 0.0, "p90": 0.0, "p10": 0.0}, {"time": "2022-04-11 00:10:00", "val": null, "median": 0.0, "p90": 0.0, "p10": 0.0}, {"time": "2022-04-11 00:20:00", "val": null, "median": 0.0, "p90": 0.0, "p10": 0.0}, {"time": "2022-04-11 00:30:00", "val": null, "median": 0.0, "p90": 0.0, "p10": 0.0}, {"time": "2022-04-11 00:40:00", "val": null, "median": 0.0, "p90": 0.0, "p10": 0.0}, {"time": "2022-04-11 00:50:00", "val": null, "median": 0.0, "p90": 0.0, "p10": 0.0}, {"time": "2022-04-11 01:00:00", "val": null, "median": 0.0, "p90": 0.0, "p10": 0.0}, {"time": "2022-04-11 01:10:00", "val": null, "median": 0.0, "p90": 0.0, "p10": 0.0}, {"time": "2022-04-11 01:20:00", "val": null, "median": 0.0, "p90": 0.0, "p10": 0.0}, {"time": "2022-04-11 01:30:00", "val": null, "median": 0.0, "p90": 0.0, "p10": 0.0}, {"time": "2022-04-11 01:40:00", "val": null, "median": 0.0, "p90": 0.0, "p10": 0.0}, {"time": "2022-04-11 01:50:00", "val": null, "median": 0.0, "p90": 0.0, "p10": 0.0}, {"time": "2022-04-11 02:00:00", "val": null, "median": 0.0, "p90": 0.0, "p10": 0.0}, {"time": "2022-04-11 02:10:00", "val": null, "median": 0.0, "p90": 0.0, "p10": 0.0}, {"time": "2022-04-11 02:20:00", "val": null, "median": 0.0, "p90": 0.0, "p10": 0.0}, {"time": "2022-04-11 02:30:00", "val": null, "median": 0.0, "p90": 0.0, "p10": 0.0}, {"time": "2022-04-11 02:40:00", "val": null, "median": 0.0, "p90": 0.0, "p10": 0.0}, {"time": "2022-04-11 02:50:00", "val": null, "median": 0.0, "p90": 0.0, "p10": 0.0}, {"time": "2022-04-11 03:00:00", "val": null, "median": 0.0, "p90": 0.0, "p10": 0.0}, {"time": "2022-04-11 03:10:00", "val": null, "median": 0.0, "p90": 0.0, "p10": 0.0}, {"time": "2022-04-11 03:20:00", "val": null, "median": 0.0, "p90": 0.0, "p10": 0.0}, {"time": "2022-04-11 03:30:00", "val": null, "median": 0.0, "p90": 0.0, "p10": 0.0}, {"time": "2022-04-11 03:40:00", "val": null, "median": 0.0, "p90": 0.0, "p10": 0.0}, {"time": "2022-04-11 03:50:00", "val": null, "median": 0.0, "p90": 0.0, "p10": 0.0}, {"time": "2022-04-11 04:00:00", "val": null, "median": 0.0, "p90": 0.0, "p10": 0.0}, {"time": "2022-04-11 04:10:00", "val": null, "median": 0.0, "p90": 0.0, "p10": 0.0}, {"time": "2022-04-11 04:20:00", "val": null, "median": 0.0, "p90": 0.0, "p10": 0.0}, {"time": "2022-04-11 04:30:00", "val": null, "median": 0.0, "p90": 0.0, "p10": 0.0}, {"time": "2022-04-11 04:40:00", "val": null, "median": 0.0, "p90": 0.0, "p10": 0.0}, {"time": "2022-04-11 04:50:00", "val": null, "median": 0.0, "p90": 0.0, "p10": 0.0}, {"time": "2022-04-11 05:00:00", "val": null, "median": 0.0, "p90": 0.0, "p10": 0.0}, {"time": "2022-04-11 05:10:00", "val": null, "median": 0.0, "p90": 0.0, "p10": 0.0}, {"time": "2022-04-11 05:20:00", "val": null, "median": 0.0, "p90": 0.0, "p10": 0.0}, {"time": "2022-04-11 05:30:00", "val": null, "median": 0.0, "p90": 2.0, "p10": 0.0}, {"time": "2022-04-11 05:40:00", "val": null, "median": 4.0, "p90": 13.0, "p10": 0.0}, {"time": "2022-04-11 05:50:00", "val": null, "median": 15.0, "p90": 30.0, "p10": 4.0}, {"time": "2022-04-11 06:00:00", "val": null, "median": 33.0, "p90": 49.0, "p10": 14.0}, {"time": "2022-04-11 06:10:00", "val": null, "median": 60.0, "p90": 77.0, "p10": 27.6}, {"time": "2022-04-11 06:20:00", "val": null, "median": 90.0, "p90": 120.0, "p10": 49.0}, {"time": "2022-04-11 06:30:00", "val": null, "median": 119.0, "p90": 172.0, "p10": 75.0}, {"time": "2022-04-11 06:40:00", "val": null, "median": 148.0, "p90": 223.0, "p10": 101.0}, {"time": "2022-04-11 06:50:00", "val": null, "median": 179.0, "p90": 235.0, "p10": 135.0}, {"time": "2022-04-11 07:00:00", "val": null, "median": 225.0, "p90": 271.0, "p10": 170.0}, {"time": "2022-04-11 07:10:00", "val": null, "median": 249.0, "p90": 318.0, "p10": 206.0}, {"time": "2022-04-11 07:20:00", "val": null, "median": 289.0, "p90": 360.0, "p10": 218.8}, {"time": "2022-04-11 07:30:00", "val": null, "median": 330.0, "p90": 401.0, "p10": 271.2}, {"time": "2022-04-11 07:40:00", "val": null, "median": 368.0, "p90": 443.0, "p10": 315.0}, {"time": "2022-04-11 07:50:00", "val": null, "median": 406.0, "p90": 479.0, "p10": 337.0}, {"time": "2022-04-11 08:00:00", "val": null, "median": 462.0, "p90": 524.0, "p10": 369.0}, {"time": "2022-04-11 08:10:00", "val": null, "median": 487.0, "p90": 551.0, "p10": 416.0}]